<?xml version="1.0" encoding="utf-8" ?><dwsync><file name=".DS_Store" server="50.87.144.171/www/swag-html/" local="3462458040" remote="20642327224" /><file name="jquery-1.10.2.min.js" server="50.87.144.171/www/swag-html/" local="3462458040" remote="20642327224" /><file name="jquery.gmap.min.js" server="50.87.144.171/www/swag-html/" local="3462458040" remote="20642327224" /><file name="jquery.validate.pack.js" server="50.87.144.171/www/swag-html/" local="3462458040" remote="20642327224" /><file name="modernizr.js" server="50.87.144.171/www/swag-html/" local="3462458040" remote="20642327224" /><file name="tinynav.js" server="50.87.144.171/www/swag-html/" local="3462458040" remote="20642327224" /><file name=".DS_Store" server="s173223.gridserver.com/html/" local="3464361960" remote="20644231144" /><file name="jquery-1.10.2.min.js" server="s173223.gridserver.com/html/" local="3464361960" remote="20644231144" /><file name="jquery.gmap.min.js" server="s173223.gridserver.com/html/" local="3464361960" remote="20644231144" /><file name="jquery.validate.pack.js" server="s173223.gridserver.com/html/" local="3464361960" remote="20644231144" /><file name="modernizr.js" server="s173223.gridserver.com/html/" local="3464361960" remote="20644231144" /><file name="tinynav.js" server="s173223.gridserver.com/html/" local="3464361960" remote="20644231144" /><file name="scripts.js" server="s173223.gridserver.com/html/" local="3464671740" remote="20644540924" /><file name="screen.js" server="s173223.gridserver.com/html/" local="3464671740" remote="20644540924" /></dwsync>